giferror.py
giferror-1.0.0.dist-info/DESCRIPTION.rst
giferror-1.0.0.dist-info/METADATA
giferror-1.0.0.dist-info/metadata.json
giferror-1.0.0.dist-info/RECORD
giferror-1.0.0.dist-info/top_level.txt
giferror-1.0.0.dist-info/WHEEL
