Metadata-Version: 2.0
Name: giferror
Version: 1.0.0
Summary: Open GIFs in exception messages in a web browser.
Home-page: https://github.com/briancurtin/giferror
Author: Brian Curtin
Author-email: brian@python.org
License: UNKNOWN
Platform: UNKNOWN
Classifier: Development Status :: 6 - Mature
Classifier: Intended Audience :: Developers
Classifier: License :: OSI Approved :: MIT License
Classifier: Programming Language :: Python :: 2
Classifier: Programming Language :: Python :: 2.7
Classifier: Programming Language :: Python :: 3
Classifier: Programming Language :: Python :: 3.3
Classifier: Programming Language :: Python :: 3.4
